dotinstall/__init__.py
dotinstall/dotinstall.py
dotinstall/installer/__init__.py
dotinstall/installer/apt_installer.py
dotinstall/installer/brew_installer.py
dotinstall/installer/eopkg_installer.py
dotinstall/installer/installer.py
dotinstall/installer/pacman_installer.py
dotinstall/installer/util.py
dotinstall/plugins/__init__.py
dotinstall/plugins/clean.py
dotinstall/plugins/dependency.py
dotinstall/plugins/link.py
dotinstall/plugins/postlink.py
dotinstall/plugins/prelink.py
dotinstall/util/__init__.py
dotinstall/util/format.py
dotinstall/util/level.py
dotinstall/util/logger.py
dotinstall/util/parser.py
dotinstall/util/path.py
dotinstall-0.10.0.dist-info/LICENSE-APACHE
dotinstall-0.10.0.dist-info/LICENSE-MIT
dotinstall-0.10.0.dist-info/METADATA
dotinstall-0.10.0.dist-info/WHEEL
dotinstall-0.10.0.dist-info/entry_points.txt
dotinstall-0.10.0.dist-info/top_level.txt
dotinstall-0.10.0.dist-info/RECORD
