Metadata-Version: 2.1
Name: dotinstall
Version: 0.10.0
Summary: Command-line tool to help install and setup your dotfiles.
Home-page: https://github.com/jeffrey-xiao/dotinstall
Author: Jeffrey Xiao
Author-email: jeffrey.xiao1998@gmail.com
License: UNKNOWN
Download-URL: https://github.com/jeffrey-xiao/dotinstall/archive/0.10.0.tar.gz
Keywords: dotfiles,commandline
Platform: UNKNOWN
Requires-Dist: PyYAML (>=5.1)
